fuzzy_json/__init__.py
fuzzy_json/decoder.py
fuzzy_json/py.typed
fuzy_jon-0.1.0.dist-info/LICENSE
fuzy_jon-0.1.0.dist-info/METADATA
fuzy_jon-0.1.0.dist-info/WHEEL
fuzy_jon-0.1.0.dist-info/RECORD
