Metadata-Version: 2.1
Name: fuzy-jon
Version: 0.1.0
Summary: 
Home-page: https://github.com/livingbio/fuzzy-json
License: MIT
Keywords: openai,json,llm
Author: lucemia
Author-email: lucemia@gmail.com
Requires-Python: >=3.10,<4.0
Classifier: Intended Audience :: Developers
Classifier: License :: OSI Approved :: MIT License
Classifier: Natural Language :: English
Classifier: Operating System :: OS Independent
Classifier: Programming Language :: Python
Classifier: Programming Language :: Python :: 3
Classifier: Programming Language :: Python :: 3.10
Classifier: Programming Language :: Python :: 3.11
Classifier: Programming Language :: Python :: 3.12
Requires-Dist: json5
Project-URL: Repository, https://github.com/livingbio/fuzzy-json
